{"1240": {"name": "卷1 帝紀第一 高祖上", "wCnt": 10137, "mCntAll": 4679, "mCntCut": 4578, "peoCntAll": 256, "peoCntCut": 72}, "1241": {"name": "卷2 帝紀第二 高祖下", "wCnt": 9799, "mCntAll": 4524, "mCntCut": 4467, "peoCntAll": 102, "peoCntCut": 34}, "1242": {"name": "卷3 帝紀第三 煬帝上", "wCnt": 6700, "mCntAll": 4542, "mCntCut": 4542, "peoCntAll": 78, "peoCntCut": 23}, "1243": {"name": "卷4 帝紀第四 煬帝下", "wCnt": 7045, "mCntAll": 4673, "mCntCut": 4641, "peoCntAll": 83, "peoCntCut": 28}, "1244": {"name": "卷5 帝紀第五 恭帝", "wCnt": 1317, "mCntAll": 647, "mCntCut": 631, "peoCntAll": 77, "peoCntCut": 12}, "1245": {"name": "卷6 志第一 禮儀一", "wCnt": 7637, "mCntAll": 111, "mCntCut": 11, "peoCntAll": 12, "peoCntCut": 1}, "1246": {"name": "卷7 志第二 禮儀二", "wCnt": 10350, "mCntAll": 67, "mCntCut": 0, "peoCntAll": 12, "peoCntCut": 0}, "1247": {"name": "卷8 志第三 禮儀三", "wCnt": 8219, "mCntAll": 137, "mCntCut": 35, "peoCntAll": 15, "peoCntCut": 1}, "1248": {"name": "卷9 志第四 禮儀四", "wCnt": 7047, "mCntAll": 62, "mCntCut": 29, "peoCntAll": 4, "peoCntCut": 1}, "1249": {"name": "卷10 志第五 禮儀五", "wCnt": 8804, "mCntAll": 243, "mCntCut": 169, "peoCntAll": 16, "peoCntCut": 3}, "1250": {"name": "卷11 志第六 禮儀六", "wCnt": 14289, "mCntAll": 100, "mCntCut": 47, "peoCntAll": 9, "peoCntCut": 2}, "1251": {"name": "卷12 志第七 禮儀七", "wCnt": 13142, "mCntAll": 116, "mCntCut": 85, "peoCntAll": 7, "peoCntCut": 2}, "1252": {"name": "卷13 志第八 音樂上", "wCnt": 9159, "mCntAll": 102, "mCntCut": 24, "peoCntAll": 16, "peoCntCut": 1}, "1253": {"name": "卷14 志第九 音樂中", "wCnt": 11673, "mCntAll": 145, "mCntCut": 69, "peoCntAll": 9, "peoCntCut": 2}, "1254": {"name": "卷15 志第十 音樂下", "wCnt": 12829, "mCntAll": 233, "mCntCut": 182, "peoCntAll": 28, "peoCntCut": 5}, "1255": {"name": "卷16 志第十一 律曆上", "wCnt": 10103, "mCntAll": 176, "mCntCut": 134, "peoCntAll": 10, "peoCntCut": 3}, "1256": {"name": "卷17 志第十二 律曆中", "wCnt": 15417, "mCntAll": 192, "mCntCut": 128, "peoCntAll": 20, "peoCntCut": 3}, "1257": {"name": "卷18 志第十三 律歷下", "wCnt": 12278, "mCntAll": 40, "mCntCut": 20, "peoCntAll": 4, "peoCntCut": 1}, "1258": {"name": "卷19 志第十四 天文上", "wCnt": 17044, "mCntAll": 317, "mCntCut": 297, "peoCntAll": 3, "peoCntCut": 1}, "1259": {"name": "卷20 志第十五 天文中", "wCnt": 13553, "mCntAll": 22, "mCntCut": 0, "peoCntAll": 2, "peoCntCut": 0}, "1260": {"name": "卷21 志第十六 天文下", "wCnt": 14784, "mCntAll": 983, "mCntCut": 885, "peoCntAll": 101, "peoCntCut": 22}, "1261": {"name": "卷22 志第十七 五行上", "wCnt": 9867, "mCntAll": 870, "mCntCut": 739, "peoCntAll": 37, "peoCntCut": 18}, "1262": {"name": "卷23 志第十八 五行下", "wCnt": 8803, "mCntAll": 489, "mCntCut": 332, "peoCntAll": 35, "peoCntCut": 10}, "1263": {"name": "卷24 志第十九 食貨", "wCnt": 9549, "mCntAll": 422, "mCntCut": 346, "peoCntAll": 19, "peoCntCut": 7}, "1264": {"name": "卷25 志第二十 刑法", "wCnt": 10312, "mCntAll": 399, "mCntCut": 264, "peoCntAll": 26, "peoCntCut": 7}, "1265": {"name": "卷26 志第二十一 百官上", "wCnt": 14160, "mCntAll": 498, "mCntCut": 340, "peoCntAll": 287, "peoCntCut": 25}, "1266": {"name": "卷27 志第二十二 百官中", "wCnt": 9229, "mCntAll": 260, "mCntCut": 86, "peoCntAll": 83, "peoCntCut": 6}, "1267": {"name": "卷28 志第二十三 百官下", "wCnt": 13170, "mCntAll": 397, "mCntCut": 234, "peoCntAll": 280, "peoCntCut": 39}, "1268": {"name": "卷29 志二十四第二十四 地理上", "wCnt": 13889, "mCntAll": 66, "mCntCut": 17, "peoCntAll": 7, "peoCntCut": 1}, "1269": {"name": "卷30 志第二十五 地理中", "wCnt": 16809, "mCntAll": 31, "mCntCut": 0, "peoCntAll": 3, "peoCntCut": 0}, "1270": {"name": "卷31 志第二十六 地理下", "wCnt": 15559, "mCntAll": 61, "mCntCut": 0, "peoCntAll": 6, "peoCntCut": 0}, "1271": {"name": "卷32 志第二十七 經籍一（經）", "wCnt": 20136, "mCntAll": 565, "mCntCut": 248, "peoCntAll": 40, "peoCntCut": 7}, "1272": {"name": "卷33 志第二十八 經籍二 （史）", "wCnt": 15537, "mCntAll": 157, "mCntCut": 0, "peoCntAll": 23, "peoCntCut": 0}, "1273": {"name": "卷34 志第二十九 經籍三 （子）", "wCnt": 19391, "mCntAll": 72, "mCntCut": 20, "peoCntAll": 6, "peoCntCut": 1}, "1274": {"name": "卷35 志第三十 經籍四 （集 道經 佛經）", "wCnt": 20594, "mCntAll": 251, "mCntCut": 50, "peoCntAll": 27, "peoCntCut": 2}, "1275": {"name": "卷36 列傳第一 后妃", "wCnt": 3532, "mCntAll": 1517, "mCntCut": 1517, "peoCntAll": 8, "peoCntCut": 4}, "1276": {"name": "卷37 列傳第二 李穆(子渾 穆兄子詢 詢弟崇 崇子敏) 梁睿", "wCnt": 6016, "mCntAll": 3458, "mCntCut": 3372, "peoCntAll": 237, "peoCntCut": 46}, "1277": {"name": "卷38 列傳第三 劉昉 鄭譯 柳裘 皇甫績(韋謩) 盧賁", "wCnt": 5708, "mCntAll": 3911, "mCntCut": 3859, "peoCntAll": 78, "peoCntCut": 11}, "1278": {"name": "卷39 列傳第四 于義(子宣道宣敏)  陰壽(子世師骨儀) 竇榮定 元景山 源雄 豆盧勣 賀若誼", "wCnt": 6093, "mCntAll": 3468, "mCntCut": 3277, "peoCntAll": 225, "peoCntCut": 45}, "1279": {"name": "卷40 列傳第五 梁士彥(子剛 梁默) 宇文忻 王誼 元諧 王世積 虞慶則 元胄", "wCnt": 6518, "mCntAll": 5006, "mCntCut": 4943, "peoCntAll": 137, "peoCntCut": 33}, "1280": {"name": "卷41 列傳第六 高熲 蘇威(子夔)", "wCnt": 5715, "mCntAll": 4984, "mCntCut": 4967, "peoCntAll": 167, "peoCntCut": 14}, "1281": {"name": "卷42 列傳第七 李德林", "wCnt": 7405, "mCntAll": 2716, "mCntCut": 2659, "peoCntAll": 67, "peoCntCut": 3}, "1282": {"name": "卷43 列傳第八 河間王弘(子慶) 楊處綱 楊子崇 觀德王雄(弟達)", "wCnt": 3032, "mCntAll": 1825, "mCntCut": 1773, "peoCntAll": 84, "peoCntCut": 8}, "1283": {"name": "卷44 列傳第九 滕穆王瓚(嗣王綸) 道悼王靜 衛昭王爽(嗣王集) 蔡王智積", "wCnt": 2283, "mCntAll": 1499, "mCntCut": 1450, "peoCntAll": 100, "peoCntCut": 11}, "1284": {"name": "卷45 列傳第十 文四子", "wCnt": 7854, "mCntAll": 5576, "mCntCut": 5549, "peoCntAll": 42, "peoCntCut": 9}, "1285": {"name": "卷46 列傳第十一 趙煚 趙芬 楊尚希 長孫平 元軍 韋師 蘇孝慈(兄子沙羅) 李雄 張煚(劉仁恩 郭均 馮世基 厙狄颭)", "wCnt": 5611, "mCntAll": 4191, "mCntCut": 4082, "peoCntAll": 269, "peoCntCut": 44}, "1286": {"name": "卷47 列傳第十二 韋世康(弟洸 弟藝 弟沖 從父弟壽) 柳機(子述 機弟旦肅 從弟雄亮 從子謇之 族兄昂 昂子調)", "wCnt": 5750, "mCntAll": 3757, "mCntCut": 3658, "peoCntAll": 125, "peoCntCut": 18}, "1287": {"name": "卷48 列傳第十三 楊素(弟約 從父文思 文紀)", "wCnt": 6655, "mCntAll": 4715, "mCntCut": 4685, "peoCntAll": 173, "peoCntCut": 26}, "1288": {"name": "卷49 列傳第十四 牛弘", "wCnt": 5823, "mCntAll": 5005, "mCntCut": 4989, "peoCntAll": 128, "peoCntCut": 10}, "1289": {"name": "卷50 列傳第十五 宇文慶 李禮成 元孝矩(弟褒) 郭榮 龐晃 李安", "wCnt": 4963, "mCntAll": 3005, "mCntCut": 2933, "peoCntAll": 256, "peoCntCut": 49}, "1290": {"name": "卷51 列傳第十六 長孫覽(從子熾 熾弟晟)", "wCnt": 4483, "mCntAll": 3717, "mCntCut": 3670, "peoCntAll": 100, "peoCntCut": 10}, "1291": {"name": "卷52 列傳第十七 韓擒虎(弟僧壽  洪) 賀若弼", "wCnt": 3381, "mCntAll": 2796, "mCntCut": 2784, "peoCntAll": 75, "peoCntCut": 17}, "1292": {"name": "卷53 列傳第十八 達奚長儒 賀婁子幹 史萬歲 劉方(馮昱 王???? 李充 楊武通 陳永貴 房兆)", "wCnt": 4793, "mCntAll": 3346, "mCntCut": 3316, "peoCntAll": 351, "peoCntCut": 77}, "1293": {"name": "卷54 列傳第十九 王長述 李衍 伊婁謙 田仁恭 元亨 杜整 李徹 崔彭", "wCnt": 3691, "mCntAll": 2118, "mCntCut": 2064, "peoCntAll": 223, "peoCntCut": 51}, "1294": {"name": "卷55 列傳第二十 杜彥 高勱 爾朱敞 周搖 獨孤楷 乞伏慧 張威 和洪 侯莫陳穎", "wCnt": 4572, "mCntAll": 2855, "mCntCut": 2844, "peoCntAll": 393, "peoCntCut": 124}, "1295": {"name": "卷56 列傳第二十一 盧愷 令狐熙 薛冑 宇文㢸 張衡 楊汪", "wCnt": 5054, "mCntAll": 4253, "mCntCut": 4223, "peoCntAll": 99, "peoCntCut": 15}, "1296": {"name": "卷57 列傳第二十二 盧思道(從父兄昌衡) 李孝貞 薛道衡(從弟孺)", "wCnt": 7550, "mCntAll": 2958, "mCntCut": 2946, "peoCntAll": 93, "peoCntCut": 14}, "1297": {"name": "卷58 列傳第二十三 明克讓 魏澹 陸爽(侯白) 杜臺卿 辛德源 柳䛒 許善心 李文博", "wCnt": 7384, "mCntAll": 4190, "mCntCut": 4099, "peoCntAll": 99, "peoCntCut": 14}, "1298": {"name": "卷59 列傳第二十四 煬三子 齊王暕 趙王杲", "wCnt": 4045, "mCntAll": 2310, "mCntCut": 2300, "peoCntAll": 44, "peoCntCut": 5}, "1299": {"name": "卷60 列傳第二十五 崔仲方 于仲文(兄顗 從父弟璽) 段文振", "wCnt": 5934, "mCntAll": 4510, "mCntCut": 4462, "peoCntAll": 154, "peoCntCut": 28}, "1300": {"name": "卷61 列傳第二十六 宇文述(雲定興) 郭衍", "wCnt": 3495, "mCntAll": 2650, "mCntCut": 2626, "peoCntAll": 138, "peoCntCut": 10}, "1301": {"name": "卷62 列傳第二十七 王韶 元巖 劉行本 梁毗 柳彧 趙綽 裴肅", "wCnt": 6461, "mCntAll": 5063, "mCntCut": 5020, "peoCntAll": 148, "peoCntCut": 21}, "1302": {"name": "卷63 列傳第二十八 樊子蓋 史祥 元壽 楊義臣 衛玄 劉權", "wCnt": 6796, "mCntAll": 4370, "mCntCut": 4336, "peoCntAll": 230, "peoCntCut": 43}, "1303": {"name": "卷64 列傳第二十九 李圓通 陳茂 張定和 張奫 麥鐵杖 沈光 來護兒 魚俱羅 陳稜 王辯(斛斯萬善)", "wCnt": 6123, "mCntAll": 4768, "mCntCut": 4717, "peoCntAll": 156, "peoCntCut": 31}, "1304": {"name": "卷65 列傳第三十 周羅睺 周法尚 李景 慕容三藏 薛世雄 王仁恭 權武 吐萬緒 董純 趙才", "wCnt": 8292, "mCntAll": 5387, "mCntCut": 5308, "peoCntAll": 163, "peoCntCut": 51}, "1305": {"name": "卷66 列傳第三十一 李諤 鮑宏 裴政 柳莊 源師 郎茂 高構 張虔威 榮毗(兄建緒) 陸知命 房彥謙", "wCnt": 9970, "mCntAll": 7455, "mCntCut": 7348, "peoCntAll": 164, "peoCntCut": 23}, "1306": {"name": "卷67 列傳第三十二 虞世基 裴蘊 裴矩", "wCnt": 6697, "mCntAll": 5316, "mCntCut": 5300, "peoCntAll": 72, "peoCntCut": 14}, "1307": {"name": "卷68 列傳第三十三 宇文愷 閻毗 何稠(劉龍 黃亙 亙弟袞)", "wCnt": 5047, "mCntAll": 4325, "mCntCut": 4303, "peoCntAll": 70, "peoCntCut": 10}, "1308": {"name": "卷69 列傳第三十四 王劭 袁充", "wCnt": 5656, "mCntAll": 5373, "mCntCut": 5373, "peoCntAll": 21, "peoCntCut": 2}, "1309": {"name": "卷70 列傳第三十五 楊玄感(李子雄 趙元淑 斛斯政 劉元進) 李密(裴仁基)", "wCnt": 9732, "mCntAll": 5687, "mCntCut": 5622, "peoCntAll": 63, "peoCntCut": 12}, "1310": {"name": "卷71 列傳第三十六 誠節", "wCnt": 7894, "mCntAll": 4840, "mCntCut": 4686, "peoCntAll": 104, "peoCntCut": 23}, "1311": {"name": "卷72 列傳第三十七 孝義", "wCnt": 3865, "mCntAll": 2739, "mCntCut": 2724, "peoCntAll": 55, "peoCntCut": 16}, "1312": {"name": "卷73 列傳第三十八 循吏", "wCnt": 6311, "mCntAll": 4874, "mCntCut": 4835, "peoCntAll": 329, "peoCntCut": 78}, "1313": {"name": "卷74 列傳第三十九 酷吏", "wCnt": 4687, "mCntAll": 3646, "mCntCut": 3633, "peoCntAll": 215, "peoCntCut": 37}, "1314": {"name": "卷75 列傳第四十 儒林", "wCnt": 8932, "mCntAll": 6446, "mCntCut": 6401, "peoCntAll": 91, "peoCntCut": 13}, "1315": {"name": "卷76 列傳第四十一 文學", "wCnt": 8010, "mCntAll": 3580, "mCntCut": 3523, "peoCntAll": 64, "peoCntCut": 14}, "1316": {"name": "卷77 列傳第四十二 隱逸", "wCnt": 4402, "mCntAll": 2631, "mCntCut": 2624, "peoCntAll": 21, "peoCntCut": 5}, "1317": {"name": "卷78 列傳第四十三 藝術", "wCnt": 9396, "mCntAll": 7538, "mCntCut": 7512, "peoCntAll": 336, "peoCntCut": 59}, "1318": {"name": "卷79 列傳第四十四 外戚", "wCnt": 3488, "mCntAll": 2225, "mCntCut": 2199, "peoCntAll": 98, "peoCntCut": 13}, "1319": {"name": "卷80 列傳第四十五 列女", "wCnt": 5743, "mCntAll": 4421, "mCntCut": 4407, "peoCntAll": 39, "peoCntCut": 15}, "1320": {"name": "卷81 列傳第四十六 東夷", "wCnt": 6750, "mCntAll": 3791, "mCntCut": 3763, "peoCntAll": 49, "peoCntCut": 7}, "1321": {"name": "卷82 列傳第四十七 南蠻", "wCnt": 3218, "mCntAll": 2520, "mCntCut": 2520, "peoCntAll": 8, "peoCntCut": 5}, "1322": {"name": "卷83 列傳第四十八 西域", "wCnt": 6928, "mCntAll": 4203, "mCntCut": 4152, "peoCntAll": 38, "peoCntCut": 26}, "1323": {"name": "卷84 列傳第四十九 北狄", "wCnt": 9616, "mCntAll": 6044, "mCntCut": 6006, "peoCntAll": 18, "peoCntCut": 8}, "1324": {"name": "卷85 列傳第五十", "wCnt": 5809, "mCntAll": 4880, "mCntCut": 4859, "peoCntAll": 41, "peoCntCut": 4}, "1325": {"name": "宋本原跋", "wCnt": 632, "mCntAll": 20, "mCntCut": 0, "peoCntAll": 3, "peoCntCut": 0}}